 <query xmlns="http://labkey.org/data/xml/query">
    <metadata> 
        <tables xmlns="http://labkey.org/data/xml">
            <table tableName="necropsies" tableDbType="TABLE">
                <tableUrl>/EHR/necropsyDetails.view?key=${objectid}</tableUrl>
                <!--<insertUrl>/ehr/manageRecord.view?schemaName=study&amp;queryName=Necropsies&amp;keyField=lsid&amp;</insertUrl>-->
                <!--<updateUrl>/ehr/manageRecord.view?schemaName=study&amp;queryName=Necropsies&amp;keyField=lsid&amp;key=${lsid}</updateUrl>-->
                <insertUrl />
                <importUrl />
                <updateUrl />
                <deleteUrl />
                <titleColumn>caseno</titleColumn>
                <columns>
                  <column columnName="participantid">
                    <datatype>varchar</datatype>
                    <columnTitle>Participant ID</columnTitle>
                    <description>Participant identifier</description>
                    <nullable>false</nullable>
                  </column>
                  <column columnName="date">
                    <datatype>timestamp</datatype>
                    <formatString>yyyy-MM-dd</formatString>
                    <columnTitle>Necropsy Date</columnTitle>
                    <nullable>false</nullable>
                    <propertyURI>http://cpas.labkey.com/Study#VisitDate</propertyURI>
                  </column>
                  <column columnName="caseno">
                    <datatype>varchar</datatype>
                    <columnTitle>Case Number</columnTitle>
                    <nullable>true</nullable>
                    <!--<isKeyField>true</isKeyField>-->
                  </column>
                  <column columnName="project">
                    <datatype>integer</datatype>
                    <nullable>true</nullable>
                    <columnTitle>Project</columnTitle>
                    <fk>
                      <fkFolderPath>/wnprc/ehr/</fkFolderPath>
                      <fkDbSchema>ehr</fkDbSchema>
                      <fkTable>project</fkTable>
                      <fkColumnName>project</fkColumnName>
                    </fk>
                    <formatString>00000000</formatString>
                    <propertyURI>urn:ehr.labkey.org/#Project</propertyURI>
                  </column>
                  <column columnName="account">
                    <datatype>varchar</datatype>
                    <columnTitle>Account</columnTitle>
                    <nullable>true</nullable>
                    <propertyURI>urn:ehr.labkey.org/#Account</propertyURI>
                  </column>
                  <column columnName="performedby">
                    <datatype>varchar</datatype>
                    <columnTitle>Pathologist</columnTitle>
                  </column>
                  <column columnName="assistant">
                    <datatype>varchar</datatype>
                    <columnTitle>Prosector</columnTitle>
                  </column>
                  <column columnName="billing">
                    <datatype>boolean</datatype>
                    <columnTitle>Billing Complete</columnTitle>
                  </column>
                  <column columnName="tissue_distribution">
                      <columnTitle>Tissue Distribution</columnTitle>
                  </column>
                  <column columnName="bcs">
                    <isHidden>true</isHidden>
                  </column>
                  <column columnName="remark">
                      <columnTitle>Final Summary Comments</columnTitle>
                  </column>
                  <column columnName="perfusion_area">
                    <datatype>varchar</datatype>
                    <columnTitle>Perfusion</columnTitle>
                    <fk>
                      <fkFolderPath>/wnprc/ehr/</fkFolderPath>
                      <fkDbSchema>ehr_lookups</fkDbSchema>
                      <fkTable>necropsy_perfusion_area</fkTable>
                      <fkColumnName>perfusion</fkColumnName>
                    </fk>
                  </column>
                  <column columnName="perfusion_soln1">
                    <datatype>varchar</datatype>
                    <isHidden>true</isHidden>
                    <columnTitle>Perfusion Solution 1</columnTitle>
                    <fk>
                      <fkFolderPath>/wnprc/ehr/</fkFolderPath>
                      <fkDbSchema>ehr_lookups</fkDbSchema>
                      <fkTable>necropsy_perfusion</fkTable>
                      <fkColumnName>perfusion</fkColumnName>
                    </fk>
                  </column>
                  <column columnName="perfusion_soln2">
                    <datatype>varchar</datatype>
                      <isHidden>true</isHidden>
                    <columnTitle>Perfusion Solution 2</columnTitle>
                    <fk>
                      <fkFolderPath>/wnprc/ehr/</fkFolderPath>
                      <fkDbSchema>ehr_lookups</fkDbSchema>
                      <fkTable>necropsy_perfusion</fkTable>
                      <fkColumnName>perfusion</fkColumnName>
                    </fk>
                  </column>
                  <column columnName="perfusion_time1">
                    <datatype>varchar</datatype>
                      <isHidden>true</isHidden>
                    <columnTitle>Perfusion Time 1</columnTitle>
                    <formatString>yyyy-MM-dd HH:mm</formatString>
                  </column>
                  <column columnName="perfusion_time2">
                    <datatype>varchar</datatype>
                      <isHidden>true</isHidden>
                    <columnTitle>Perfusion Time 2</columnTitle>
                    <formatString>yyyy-MM-dd HH:mm</formatString>
                  </column>
                  <column columnName="bcs">
                    <datatype>varchar</datatype>
                    <columnTitle>Body Condition</columnTitle>
                    <fk>
                      <fkFolderPath>/wnprc/ehr/</fkFolderPath>
                      <fkDbSchema>ehr_lookups</fkDbSchema>
                      <fkTable>necropsy_condition</fkTable>
                      <fkColumnName>score</fkColumnName>
                    </fk>
                  </column>
                  <column columnName="patho_notes">
                    <datatype>varchar</datatype>
                    <inputType>textarea</inputType>
                    <columnTitle>Pathology Unit Notes</columnTitle>
                  </column>
                  <column columnName="histopathologic">
                      <columnTitle>Histopathologic Description</columnTitle>
                  </column>
                  <column columnName="final_description">
                    <datatype>varchar</datatype>
                    <inputType>textarea</inputType>
                    <columnTitle>Final Description</columnTitle>
                  </column>
                  <column columnName="description">
                    <datatype>varchar</datatype>
                    <columnTitle>Description</columnTitle>
                    <shownInInsertView>false</shownInInsertView>
                    <shownInUpdateView>false</shownInUpdateView>
                    <shownInDetailsView>false</shownInDetailsView>
                    <propertyURI>urn:ehr.labkey.org/#Description</propertyURI>
                    <isHidden>true</isHidden>
                    <inputType>textarea</inputType>
                  </column>
                  <column columnName="objectid">
                    <datatype>entityid</datatype>
                    <columnTitle>Key</columnTitle>
                    <shownInInsertView>false</shownInInsertView>
                    <shownInUpdateView>false</shownInUpdateView>
                    <shownInDetailsView>false</shownInDetailsView>
                    <isHidden>true</isHidden>
                    <!--<isKeyField>true</isKeyField>-->
                  </column>
                  <column columnName="parentId">
                    <datatype>varchar</datatype>
                    <columnTitle>Parent Id</columnTitle>
                    <propertyURI>urn:ehr.labkey.org/#ParentId</propertyURI>
                    <!--<fk>-->
                      <!--<fkFolderPath>/wnprc/ehr/</fkFolderPath>-->
                      <!--<fkDbSchema>study</fkDbSchema>-->
                      <!--<fkTable>studyDataParent</fkTable>-->
                      <!--<fkColumnName>objectid</fkColumnName>-->
                    <!--</fk>-->
                  </column>
                  <column columnName="requestid">
                    <datatype>varchar</datatype>
                    <columnTitle>Request Id</columnTitle>
                    <isHidden>true</isHidden>
                    <shownInInsertView>false</shownInInsertView>
                    <shownInUpdateView>false</shownInUpdateView>
                  </column>
                  <column columnName="ts">
                    <datatype>timestamp</datatype>
                    <columnTitle>Last Changed</columnTitle>
                    <!--<nullable>false</nullable>-->
                    <shownInInsertView>false</shownInInsertView>
                    <shownInUpdateView>false</shownInUpdateView>
                    <shownInDetailsView>false</shownInDetailsView>
                    <isHidden>true</isHidden>
                  </column>
                  <column columnName="timeofdeath">
                      <columnTitle>Time of Death</columnTitle>
                  </column>
                  <column columnName="nhpbmd">
                      <columnTitle>NHPBMD</columnTitle>
                  </column>
                  <column columnName="grossdescription">
                      <columnTitle>Gross Morphologic Description</columnTitle>
                      <inputType>textarea</inputType>
                  </column>
                  <column columnName="comments">
                      <columnTitle>Comments</columnTitle>
                      <inputType>textarea</inputType>
                  </column>
                  <column columnName="causeofdeath">
                    <datatype>varchar</datatype>
                    <columnTitle>Type of Death</columnTitle>
                    <fk>
                      <fkFolderPath>/wnprc/ehr/</fkFolderPath>
                      <fkDbSchema>ehr_lookups</fkDbSchema>
                      <fkTable>death_cause</fkTable>
                      <fkColumnName>cause</fkColumnName>
                    </fk>
                  </column>
                  <column columnName="mannerofdeath">
                    <datatype>varchar</datatype>
                    <columnTitle>Manner of Death</columnTitle>
                    <fk>
                      <fkFolderPath>/wnprc/ehr/</fkFolderPath>
                      <fkDbSchema>ehr_lookups</fkDbSchema>
                      <fkTable>death_manner</fkTable>
                      <fkColumnName>manner</fkColumnName>
                    </fk>
                  </column>
                    <column columnName="tattoo">
                      <columnTitle>Tattoo/Tag</columnTitle>
                    </column>
                </columns>
                <tableTitle>Necropsies</tableTitle>
            </table>
        </tables>
    </metadata>
</query>